Metadata-Version: 2.4
Name: freenect
Version: 0.1.0
Summary: Python wrapper for libfreenect - Microsoft Kinect library
Author-email: Dewmina Wijekoon <dewmandula@gmail.com>
Maintainer-email: Dewmina Wijekoon <dewmandula@gmail.com>
License-Expression: MIT
Project-URL: Homepage, https://github.com/dewminawijekoon/freenect-python
Project-URL: Documentation, https://github.com/dewminawijekoon/freenect-python#readme
Project-URL: Repository, https://github.com/dewminawijekoon/freenect-python.git
Project-URL: Bug Tracker, https://github.com/dewminawijekoon/freenect-python/issues
Keywords: kinect,freenect,computer-vision,depth-camera
Classifier: Development Status :: 4 - Beta
Classifier: Intended Audience :: Developers
Classifier: Operating System :: OS Independent
Classifier: Programming Language :: Python :: 3
Classifier: Programming Language :: Python :: 3.8
Classifier: Programming Language :: Python :: 3.9
Classifier: Programming Language :: Python :: 3.10
Classifier: Programming Language :: Python :: 3.11
Classifier: Programming Language :: Python :: 3.12
Classifier: Programming Language :: Cython
Classifier: Topic :: Multimedia :: Graphics :: Capture
Classifier: Topic :: Scientific/Engineering
Classifier: Topic :: Software Development :: Libraries :: Python Modules
Requires-Python: >=3.8
License-File: LICENSE
Requires-Dist: numpy>=1.19.0
Provides-Extra: dev
Requires-Dist: pytest>=6.0; extra == "dev"
Requires-Dist: pytest-cov; extra == "dev"
Requires-Dist: black; extra == "dev"
Requires-Dist: flake8; extra == "dev"
Requires-Dist: mypy; extra == "dev"
Provides-Extra: docs
Requires-Dist: sphinx; extra == "docs"
Requires-Dist: sphinx-rtd-theme; extra == "docs"
Dynamic: license-file
